Metadata-Version: 2.1
Name: kmersfasta
Version: 0.0.2
Summary: Display and count k-mers from the fasta file
Home-page: UNKNOWN
Author: Roshan Shrestha
License: UNKNOWN
Platform: UNKNOWN
Requires-Python: >3.6.0
